merkle_tree.py
setup.cfg
setup.py
merkle_tree.egg-info/PKG-INFO
merkle_tree.egg-info/SOURCES.txt
merkle_tree.egg-info/dependency_links.txt
merkle_tree.egg-info/entry_points.txt
merkle_tree.egg-info/requires.txt
merkle_tree.egg-info/top_level.txt