Metadata-Version: 1.1
Name: merkle-tree
Version: 0.2
Summary: CLI to calculate Merkle Tree based on botocore implementation.
Home-page: https://github.com/quiver/merkle_tree
Author: George Yoshida
Author-email: UNKNOWN
License: Apache Licenset 2.0
Platform: UNKNOWN
Classifier: Development Status :: 3 - Alpha
Classifier: Intended Audience :: Developers
Classifier: Intended Audience :: System Administrators
Classifier: Natural Language :: English
Classifier: License :: OSI Approved :: Apache Software License
Classifier: Programming Language :: Python
Classifier: Programming Language :: Python :: 2.6
Classifier: Programming Language :: Python :: 2.7
Classifier: Programming Language :: Python :: 3
Classifier: Programming Language :: Python :: 3.3
